LICENSE
MANIFEST.in
README.rst
setup.py
bootstrap4form/__init__.py
bootstrap4form/config.py
bootstrap4form/meta.py
bootstrap4form/models.py
bootstrap4form/tests.py
bootstrap4form/templates/bootstrap4form/field.html
bootstrap4form/templates/bootstrap4form/form.html
bootstrap4form/templates/bootstrap4form/formset.html
bootstrap4form/templatetags/__init__.py
bootstrap4form/templatetags/bootstrap4form.py
django_bootstrap4_form.egg-info/PKG-INFO
django_bootstrap4_form.egg-info/SOURCES.txt
django_bootstrap4_form.egg-info/dependency_links.txt
django_bootstrap4_form.egg-info/not-zip-safe
django_bootstrap4_form.egg-info/requires.txt
django_bootstrap4_form.egg-info/top_level.txt
tests/test_settings.py