Metadata-Version: 2.1
Name: django-bootstrap4-form
Version: 4.0.2
Summary: django-bootstrap4-form
Home-page: http://github.com/gwasser/django-bootstrap4-form
Author: gwasser
Author-email: garret@wassiverse.com
License: MIT
Keywords: bootstrap4,django
Classifier: Programming Language :: Python
Classifier: Topic :: Software Development :: Libraries :: Python Modules
Classifier: Framework :: Django
Classifier: Framework :: Django :: 2.2
Classifier: Environment :: Web Environment
Classifier: Programming Language :: Python :: 3
Classifier: Programming Language :: Python :: 3.8
Classifier: Programming Language :: Python :: 3.9
Classifier: Programming Language :: Python :: 3.10
Classifier: Programming Language :: Python :: 3.11
Classifier: Programming Language :: Python :: 3.12
License-File: LICENSE
Requires-Dist: django>=2.2
